flash/__init__.py
flash/__main__.py
flash/src/__init__.py
flash/src/flash.py
flash/src/flash_error.py
flash/src/flashio.py
flash/src/frame.py
flash_frame-0.1.8.dist-info/METADATA
flash_frame-0.1.8.dist-info/WHEEL
flash_frame-0.1.8.dist-info/top_level.txt
flash_frame-0.1.8.dist-info/RECORD
